gfx2cuda/__init__.py
gfx2cuda/backends.py
gfx2cuda/dll/__init__.py
gfx2cuda/dll/cuda.py
gfx2cuda/dll/d3d.py
gfx2cuda/dll/dxgi.py
gfx2cuda/exception.py
gfx2cuda/format.py
gfx2cuda/gfx2cuda.py
gfx2cuda-0.0.2.dist-info/LICENSE
gfx2cuda-0.0.2.dist-info/WHEEL
gfx2cuda-0.0.2.dist-info/METADATA
gfx2cuda-0.0.2.dist-info/RECORD
