Metadata-Version: 2.1
Name: gfx2cuda
Version: 0.0.2
Summary: Fast graphics texture to cuda transfer
Home-page: https://github.com/SvenDH/
License: MIT
Keywords: Screen Capture,Screenshot,Computer Vision
Author: Sven den Hartog
Author-email: denhartog.sven@gmail.com
Requires-Python: >=3.6
Classifier: Development Status :: 5 - Production/Stable
Classifier: Intended Audience :: Developers
Classifier: License :: OSI Approved :: MIT License
Classifier: Natural Language :: English
Classifier: Programming Language :: Python
Classifier: Programming Language :: Python :: 3
Classifier: Programming Language :: Python :: 3.10
Classifier: Programming Language :: Python :: 3.6
Classifier: Programming Language :: Python :: 3.7
Classifier: Programming Language :: Python :: 3.8
Classifier: Programming Language :: Python :: 3.9
Classifier: Topic :: Multimedia :: Graphics
Classifier: Topic :: Multimedia :: Graphics :: Capture
Requires-Dist: comtypes (>=1.1.7,<1.2.0)
Requires-Dist: numpy (>=1.16.5,<1.17.0)
Project-URL: Repository, https://github.com/SvenDH/
